Metadata-Version: 2.1
Name: odoo12-addon-l10n-es-account-asset
Version: 12.0.2.0.8
Summary: Gestión de activos fijos para España
Home-page: https://github.com/OCA/l10n-spain
Author: Tecnativa, Odoo Community Association (OCA)
Author-email: support@odoo-community.org
License: AGPL-3
Platform: UNKNOWN
Classifier: Programming Language :: Python
Classifier: Framework :: Odoo
Classifier: Framework :: Odoo :: 12.0
Classifier: License :: OSI Approved :: GNU Affero General Public License v3
Classifier: Development Status :: 5 - Production/Stable
Requires-Python: >=3.5
Requires-Dist: odoo12-addon-account-asset-management
Requires-Dist: odoo <12.1dev,>=12.0a
